seabornWrapper/__init__.py
seabornWrapper/flexiblePlots.py
seabornWrapper-0.0.2.dist-info/LICENSE
seabornWrapper-0.0.2.dist-info/METADATA
seabornWrapper-0.0.2.dist-info/WHEEL
seabornWrapper-0.0.2.dist-info/top_level.txt
seabornWrapper-0.0.2.dist-info/RECORD
